launch/__init__.py
launch/__main__.py
launch/launch.py
launch/main.py
launch/test.py
launch/data/__init__.py
launch/environment/__init__.py
launch/environment/environment.py
launch/unittest/__init__.py
launch/unittest/test_launch.py
launch/utils/__init__.py
launch/utils/utils.py
launchenv-0.0.4.dist-info/LICENSE
launchenv-0.0.4.dist-info/METADATA
launchenv-0.0.4.dist-info/WHEEL
launchenv-0.0.4.dist-info/entry_points.txt
launchenv-0.0.4.dist-info/top_level.txt
launchenv-0.0.4.dist-info/RECORD
