Metadata-Version: 2.1
Name: launchenv
Version: 0.0.4
Summary: Launch all your programs and scripts with one command
Home-page: https://github.com/a-tharva/LaunchEnv
Author: Atharva Bhandvalkar
Author-email: <atharv.bhandvalkar@gmail.com>
License: MIT
Keywords: python
Platform: UNKNOWN
Classifier: Development Status :: 4 - Beta
Classifier: Intended Audience :: Developers
Classifier: License :: OSI Approved :: MIT License
Classifier: Programming Language :: Python :: 3
Classifier: Operating System :: Unix
Classifier: Operating System :: MacOS :: MacOS X
Classifier: Operating System :: Microsoft :: Windows
